{"Routes": [], "Quotes": [{"QuoteId": 1, "MinPrice": 201.0, "Direct": true, "OutboundLeg": {"CarrierIds": [1368], "OriginId": 44759, "DestinationId": 52337, "DepartureDate": "2020-01-15T00:00:00"}, "QuoteDateTime": "2020-01-14T16:30:00"}, {"QuoteId": 2, "MinPrice": 103.0, "Direct": false, "OutboundLeg": {"CarrierIds": [1816], "OriginId": 73097, "DestinationId": 52337, "DepartureDate": "2020-01-16T00:00:00"}, "QuoteDateTime": "2020-01-12T17:20:00"}, {"QuoteId": 3, "MinPrice": 173.0, "Direct": true, "OutboundLeg": {"CarrierIds": [1368], "OriginId": 44759, "DestinationId": 52337, "DepartureDate": "2020-01-16T00:00:00"}, "QuoteDateTime": "2020-01-12T17:20:00"}, {"QuoteId": 4, "MinPrice": 108.0, "Direct": false, "OutboundLeg": {"CarrierIds": [1090], "OriginId": 43313, "DestinationId": 52337, "DepartureDate": "2020-01-17T00:00:00"}, "QuoteDateTime": "2020-01-14T22:28:00"}, {"QuoteId": 5, "MinPrice": 170.0, "Direct": true, "OutboundLeg": {"CarrierIds": [838], "OriginId": 44759, "DestinationId": 52337, "DepartureDate": "2020-01-17T00:00:00"}, "QuoteDateTime": "2020-01-14T22:28:00"}, {"QuoteId": 6, "MinPrice": 81.0, "Direct": false, "OutboundLeg": {"CarrierIds": [1816], "OriginId": 73097, "DestinationId": 52337, "DepartureDate": "2020-01-18T00:00:00"}, "QuoteDateTime": "2020-01-12T11:48:00"}, {"QuoteId": 7, "MinPrice": 117.0, "Direct": true, "OutboundLeg": {"CarrierIds": [1368], "OriginId": 44759, "DestinationId": 52337, "DepartureDate": "2020-01-18T00:00:00"}, "QuoteDateTime": "2020-01-12T11:48:00"}, {"QuoteId": 8, "MinPrice": 145.0, "Direct": true, "OutboundLeg": {"CarrierIds": [1368], "OriginId": 44759, "DestinationId": 52337, "DepartureDate": "2020-01-19T00:00:00"}, "QuoteDateTime": "2020-01-14T18:48:00"}, {"QuoteId": 9, "MinPrice": 81.0, "Direct": false, "OutboundLeg": {"CarrierIds": [1090], "OriginId": 43313, "DestinationId": 52337, "DepartureDate": "2020-01-19T00:00:00"}, "QuoteDateTime": "2020-01-14T21:22:00"}, {"QuoteId": 10, "MinPrice": 156.0, "Direct": true, "OutboundLeg": {"CarrierIds": [838], "OriginId": 44759, "DestinationId": 52337, "DepartureDate": "2020-01-20T00:00:00"}, "QuoteDateTime": "2020-01-14T22:45:00"}, {"QuoteId": 11, "MinPrice": 79.0, "Direct": false, "OutboundLeg": {"CarrierIds": [1090], "OriginId": 43313, "DestinationId": 56478, "DepartureDate": "2020-01-20T00:00:00"}, "QuoteDateTime": "2020-01-14T22:45:00"}, {"QuoteId": 12, "MinPrice": 99.0, "Direct": true, "OutboundLeg": {"CarrierIds": [1368], "OriginId": 44759, "DestinationId": 52337, "DepartureDate": "2020-01-21T00:00:00"}, "QuoteDateTime": "2020-01-08T00:34:00"}, {"QuoteId": 13, "MinPrice": 43.0, "Direct": false, "OutboundLeg": {"CarrierIds": [1878], "OriginId": 43313, "DestinationId": 56478, "DepartureDate": "2020-01-21T00:00:00"}, "QuoteDateTime": "2020-01-14T21:58:00"}, {"QuoteId": 14, "MinPrice": 41.0, "Direct": false, "OutboundLeg": {"CarrierIds": [1090], "OriginId": 43313, "DestinationId": 56478, "DepartureDate": "2020-01-22T00:00:00"}, "QuoteDateTime": "2020-01-14T20:51:00"}, {"QuoteId": 15, "MinPrice": 99.0, "Direct": true, "OutboundLeg": {"CarrierIds": [1368], "OriginId": 44759, "DestinationId": 52337, "DepartureDate": "2020-01-22T00:00:00"}, "QuoteDateTime": "2020-01-08T15:49:00"}, {"QuoteId": 16, "MinPrice": 57.0, "Direct": false, "OutboundLeg": {"CarrierIds": [1090], "OriginId": 43313, "DestinationId": 52337, "DepartureDate": "2020-01-23T00:00:00"}, "QuoteDateTime": "2020-01-14T22:34:00"}, {"QuoteId": 17, "MinPrice": 145.0, "Direct": true, "OutboundLeg": {"CarrierIds": [1368], "OriginId": 44759, "DestinationId": 52337, "DepartureDate": "2020-01-23T00:00:00"}, "QuoteDateTime": "2020-01-10T18:13:00"}, {"QuoteId": 18, "MinPrice": 89.0, "Direct": false, "OutboundLeg": {"CarrierIds": [50441], "OriginId": 44759, "DestinationId": 56478, "DepartureDate": "2020-01-24T00:00:00"}, "QuoteDateTime": "2020-01-14T22:02:00"}, {"QuoteId": 19, "MinPrice": 100.0, "Direct": true, "OutboundLeg": {"CarrierIds": [1368], "OriginId": 44759, "DestinationId": 52337, "DepartureDate": "2020-01-24T00:00:00"}, "QuoteDateTime": "2020-01-14T22:02:00"}, {"QuoteId": 20, "MinPrice": 48.0, "Direct": false, "OutboundLeg": {"CarrierIds": [1878], "OriginId": 43313, "DestinationId": 56478, "DepartureDate": "2020-01-25T00:00:00"}, "QuoteDateTime": "2020-01-14T21:35:00"}, {"QuoteId": 21, "MinPrice": 66.0, "Direct": true, "OutboundLeg": {"CarrierIds": [1368], "OriginId": 44759, "DestinationId": 52337, "DepartureDate": "2020-01-25T00:00:00"}, "QuoteDateTime": "2020-01-07T13:38:00"}, {"QuoteId": 22, "MinPrice": 83.0, "Direct": true, "OutboundLeg": {"CarrierIds": [1368], "OriginId": 44759, "DestinationId": 52337, "DepartureDate": "2020-01-26T00:00:00"}, "QuoteDateTime": "2020-01-11T21:12:00"}, {"QuoteId": 23, "MinPrice": 67.0, "Direct": false, "OutboundLeg": {"CarrierIds": [1865], "OriginId": 44759, "DestinationId": 56478, "DepartureDate": "2020-01-26T00:00:00"}, "QuoteDateTime": "2020-01-14T20:36:00"}, {"QuoteId": 24, "MinPrice": 59.0, "Direct": false, "OutboundLeg": {"CarrierIds": [1090], "OriginId": 43313, "DestinationId": 52337, "DepartureDate": "2020-01-27T00:00:00"}, "QuoteDateTime": "2020-01-14T21:07:00"}, {"QuoteId": 25, "MinPrice": 83.0, "Direct": true, "OutboundLeg": {"CarrierIds": [1368], "OriginId": 44759, "DestinationId": 52337, "DepartureDate": "2020-01-27T00:00:00"}, "QuoteDateTime": "2020-01-09T00:01:00"}, {"QuoteId": 26, "MinPrice": 42.0, "Direct": false, "OutboundLeg": {"CarrierIds": [1878], "OriginId": 43313, "DestinationId": 56478, "DepartureDate": "2020-01-28T00:00:00"}, "QuoteDateTime": "2020-01-14T19:28:00"}, {"QuoteId": 27, "MinPrice": 83.0, "Direct": true, "OutboundLeg": {"CarrierIds": [1368], "OriginId": 44759, "DestinationId": 52337, "DepartureDate": "2020-01-28T00:00:00"}, "QuoteDateTime": "2020-01-14T19:28:00"}, {"QuoteId": 28, "MinPrice": 42.0, "Direct": false, "OutboundLeg": {"CarrierIds": [1878], "OriginId": 43313, "DestinationId": 52337, "DepartureDate": "2020-01-29T00:00:00"}, "QuoteDateTime": "2020-01-14T21:52:00"}, {"QuoteId": 29, "MinPrice": 88.0, "Direct": true, "OutboundLeg": {"CarrierIds": [1368], "OriginId": 44759, "DestinationId": 52337, "DepartureDate": "2020-01-29T00:00:00"}, "QuoteDateTime": "2020-01-14T21:52:00"}, {"QuoteId": 30, "MinPrice": 83.0, "Direct": true, "OutboundLeg": {"CarrierIds": [1368], "OriginId": 44759, "DestinationId": 52337, "DepartureDate": "2020-01-30T00:00:00"}, "QuoteDateTime": "2020-01-10T13:07:00"}, {"QuoteId": 31, "MinPrice": 49.0, "Direct": false, "OutboundLeg": {"CarrierIds": [1090], "OriginId": 43313, "DestinationId": 56478, "DepartureDate": "2020-01-30T00:00:00"}, "QuoteDateTime": "2020-01-14T20:23:00"}, {"QuoteId": 32, "MinPrice": 66.0, "Direct": true, "OutboundLeg": {"CarrierIds": [1368], "OriginId": 44759, "DestinationId": 52337, "DepartureDate": "2020-01-31T00:00:00"}, "QuoteDateTime": "2020-01-13T21:45:00"}, {"QuoteId": 33, "MinPrice": 54.0, "Direct": false, "OutboundLeg": {"CarrierIds": [1090], "OriginId": 43313, "DestinationId": 52337, "DepartureDate": "2020-01-31T00:00:00"}, "QuoteDateTime": "2020-01-14T22:32:00"}], "Places": [{"PlaceId": 43313, "IataCode": "BVA", "Name": "Paris Beauvais", "Type": "Station", "SkyscannerCode": "BVA", "CityName": "Paris", "CityId": "PARI", "CountryName": "France"}, {"PlaceId": 44759, "IataCode": "CDG", "Name": "Paris Charles de Gaulle", "Type": "Station", "SkyscannerCode": "CDG", "CityName": "Paris", "CityId": "PARI", "CountryName": "France"}, {"PlaceId": 52337, "IataCode": "FRA", "Name": "Frankfurt am Main", "Type": "Station", "SkyscannerCode": "FRA", "CityName": "Frankfurt", "CityId": "FRAN", "CountryName": "Germany"}, {"PlaceId": 56478, "IataCode": "HHN", "Name": "Frankfurt Hahn", "Type": "Station", "SkyscannerCode": "HHN", "CityName": "Frankfurt", "CityId": "FRAN", "CountryName": "Germany"}, {"PlaceId": 73097, "IataCode": "ORY", "Name": "Paris Orly", "Type": "Station", "SkyscannerCode": "ORY", "CityName": "Paris", "CityId": "PARI", "CountryName": "France"}], "Carriers": [{"CarrierId": 838, "Name": "Air France"}, {"CarrierId": 50441, "Name": "easyJet"}, {"CarrierId": 1090, "Name": "Ryanair"}, {"CarrierId": 1368, "Name": "Lufthansa"}, {"CarrierId": 1816, "Name": "Air Europa"}, {"CarrierId": 1865, "Name": "Vueling Airlines"}, {"CarrierId": 1878, "Name": "Wizz Air"}], "Currencies": [{"Code": "EUR", "Symbol": "\u00e2\u201a\u00ac", "ThousandsSeparator": ".", "DecimalSeparator": ",", "SymbolOnLeft": false, "SpaceBetweenAmountAndSymbol": true, "RoundingCoefficient": 0, "DecimalDigits": 2}]}
